awstools/__init__.py
awstools/_aws.py
awstools/ec2.py
awstools/encryption.py
awstools/events.py
awstools/s3.py
awstools/setup.py
awstools/transcoder.py
awstools/utils.py
awstools/watermark.py
awstools_py-0.1.3.dist-info/LICENSE
awstools_py-0.1.3.dist-info/METADATA
awstools_py-0.1.3.dist-info/WHEEL
awstools_py-0.1.3.dist-info/top_level.txt
awstools_py-0.1.3.dist-info/RECORD
