Metadata-Version: 2.1
Name: awstools-py
Version: 0.1.3
Summary: Simple wrappers for boto3 to make life easier
Home-page: https://github.com/jaredlunde/awstools
Author: Jared Lunde
Author-email: jared.lunde@gmail.com
License: MIT
Platform: UNKNOWN
Requires-Dist: boto3
Requires-Dist: configparser
